{
  "LSVM_A": 320,
  "LSVM_B": 10,
  "proximity": [
    {
      "rowPosition": 0,
      "columnPosition": 0,
      "id": 0,
      "worldId": 854
    },
    {
      "rowPosition": 0,
      "columnPosition": 1,
      "id": 1,
      "worldId": 854
    },
    {
      "rowPosition": 0,
      "columnPosition": 2,
      "id": 2,
      "worldId": 854
    },
    {
      "rowPosition": 0,
      "columnPosition": 3,
      "id": 3,
      "worldId": 854
    },
    {
      "rowPosition": 0,
      "columnPosition": 4,
      "id": 4,
      "worldId": 854
    },
    {
      "rowPosition": 0,
      "columnPosition": 5,
      "id": 5,
      "worldId": 854
    },
    {
      "rowPosition": 1,
      "columnPosition": 0,
      "id": 6,
      "worldId": 854
    },
    {
      "rowPosition": 1,
      "columnPosition": 1,
      "id": 7,
      "worldId": 854
    },
    {
      "rowPosition": 1,
      "columnPosition": 2,
      "id": 8,
      "worldId": 854
    },
    {
      "rowPosition": 1,
      "columnPosition": 3,
      "id": 9,
      "worldId": 854
    },
    {
      "rowPosition": 1,
      "columnPosition": 4,
      "id": 10,
      "worldId": 854
    },
    {
      "rowPosition": 1,
      "columnPosition": 5,
      "id": 11,
      "worldId": 854
    },
    {
      "rowPosition": 2,
      "columnPosition": 0,
      "id": 12,
      "worldId": 854
    },
    {
      "rowPosition": 2,
      "columnPosition": 1,
      "id": 13,
      "worldId": 854
    },
    {
      "rowPosition": 2,
      "columnPosition": 2,
      "id": 14,
      "worldId": 854
    },
    {
      "rowPosition": 2,
      "columnPosition": 3,
      "id": 15,
      "worldId": 854
    },
    {
      "rowPosition": 2,
      "columnPosition": 4,
      "id": 16,
      "worldId": 854
    },
    {
      "rowPosition": 2,
      "columnPosition": 5,
      "id": 17,
      "worldId": 854
    }
  ],
  "values": {
    "0": 4.17161299674346341959108031005598604679107666015625,
    "1": 7.084297426462665470126012223772704601287841796875,
    "2": 6.3069987002180436519438444520346820354461669921875,
    "3": 6.723486927957427639057641499675810337066650390625,
    "4": 8.126992135145261642037439742125570774078369140625,
    "5": 6.38126142904282200873922192840836942195892333984375,
    "6": 8.19163982946570712329048546962440013885498046875,
    "7": 4.0012078321113602186187563347630202770233154296875,
    "8": 6.829362996087308346204736153595149517059326171875,
    "9": 6.46712999882833461384734619059599936008453369140625,
    "10": 7.472123619362644575403464841656386852264404296875,
    "11": 6.55881272287061367620708551839925348758697509765625,
    "12": 7.288976924861824358004014356993138790130615234375,
    "13": 8.92169807187460861541694612242281436920166015625,
    "14": 3.203613621016296431065484284772537648677825927734375,
    "15": 8.17801528769275165586805087514221668243408203125,
    "16": 7.2004527604672592389078999985940754413604736328125,
    "17": 3.840897910436581685900137017597444355487823486328125
  },
  "setupType": "National Bidder Setup",
  "population": 0,
  "id": 0,
  "worldId": 854,
  "setup": {
    "valueInterval": {
      "minValue": 3.0,
      "maxValue": 9.0
    },
    "proximitySize": -1,
    "a": 320,
    "b": 10,
    "setupName": "National Bidder Setup",
    "numberOfBidders": 1
  },
  "implementation": "org.spectrumauctions.sats.core.model.lsvm.LSVMBidder"
}