{
  "LSVM_A": 320,
  "LSVM_B": 10,
  "proximity": [
    {
      "rowPosition": 0,
      "columnPosition": 0,
      "id": 0,
      "worldId": 348
    },
    {
      "rowPosition": 0,
      "columnPosition": 1,
      "id": 1,
      "worldId": 348
    },
    {
      "rowPosition": 0,
      "columnPosition": 2,
      "id": 2,
      "worldId": 348
    },
    {
      "rowPosition": 0,
      "columnPosition": 3,
      "id": 3,
      "worldId": 348
    },
    {
      "rowPosition": 0,
      "columnPosition": 4,
      "id": 4,
      "worldId": 348
    },
    {
      "rowPosition": 0,
      "columnPosition": 5,
      "id": 5,
      "worldId": 348
    },
    {
      "rowPosition": 1,
      "columnPosition": 0,
      "id": 6,
      "worldId": 348
    },
    {
      "rowPosition": 1,
      "columnPosition": 1,
      "id": 7,
      "worldId": 348
    },
    {
      "rowPosition": 1,
      "columnPosition": 2,
      "id": 8,
      "worldId": 348
    },
    {
      "rowPosition": 1,
      "columnPosition": 3,
      "id": 9,
      "worldId": 348
    },
    {
      "rowPosition": 1,
      "columnPosition": 4,
      "id": 10,
      "worldId": 348
    },
    {
      "rowPosition": 1,
      "columnPosition": 5,
      "id": 11,
      "worldId": 348
    },
    {
      "rowPosition": 2,
      "columnPosition": 0,
      "id": 12,
      "worldId": 348
    },
    {
      "rowPosition": 2,
      "columnPosition": 1,
      "id": 13,
      "worldId": 348
    },
    {
      "rowPosition": 2,
      "columnPosition": 2,
      "id": 14,
      "worldId": 348
    },
    {
      "rowPosition": 2,
      "columnPosition": 3,
      "id": 15,
      "worldId": 348
    },
    {
      "rowPosition": 2,
      "columnPosition": 4,
      "id": 16,
      "worldId": 348
    },
    {
      "rowPosition": 2,
      "columnPosition": 5,
      "id": 17,
      "worldId": 348
    }
  ],
  "values": {
    "0": 7.506300344121743961522952304221689701080322265625,
    "1": 6.06804785689489989408684778027236461639404296875,
    "2": 6.566303347708529969395385705865919589996337890625,
    "3": 6.2104626955195865178893654956482350826263427734375,
    "4": 4.83737032806724531752706752740778028964996337890625,
    "5": 8.6162314167360936068007504218257963657379150390625,
    "6": 5.45477805963607220718358803424052894115447998046875,
    "7": 4.08471874998432138426096571492962539196014404296875,
    "8": 7.4001979021946766579276300035417079925537109375,
    "9": 3.979158123140382752325194815057329833507537841796875,
    "10": 4.21137149185074388668681422132067382335662841796875,
    "11": 4.4361027605296410314394961460493505001068115234375,
    "12": 3.374396565391929669885939802043139934539794921875,
    "13": 7.5468516007569093062556930817663669586181640625,
    "14": 8.3445856881405884308833265095017850399017333984375,
    "15": 8.495642139037482110097698750905692577362060546875,
    "16": 8.662112799542388330564790521748363971710205078125,
    "17": 3.121752983914750867455722982413135468959808349609375
  },
  "setupType": "National Bidder Setup",
  "population": 0,
  "id": 0,
  "worldId": 348,
  "setup": {
    "valueInterval": {
      "minValue": 3.0,
      "maxValue": 9.0
    },
    "proximitySize": -1,
    "a": 320,
    "b": 10,
    "setupName": "National Bidder Setup",
    "numberOfBidders": 1
  },
  "implementation": "org.spectrumauctions.sats.core.model.lsvm.LSVMBidder"
}