{
  "LSVM_A": 160,
  "LSVM_B": 4,
  "proximity": [
    {
      "rowPosition": 1,
      "columnPosition": 5,
      "id": 11,
      "worldId": 209
    },
    {
      "rowPosition": 1,
      "columnPosition": 3,
      "id": 9,
      "worldId": 209
    },
    {
      "rowPosition": 1,
      "columnPosition": 4,
      "id": 10,
      "worldId": 209
    },
    {
      "rowPosition": 1,
      "columnPosition": 1,
      "id": 7,
      "worldId": 209
    },
    {
      "rowPosition": 1,
      "columnPosition": 2,
      "id": 8,
      "worldId": 209
    },
    {
      "rowPosition": 0,
      "columnPosition": 3,
      "id": 3,
      "worldId": 209
    },
    {
      "rowPosition": 0,
      "columnPosition": 4,
      "id": 4,
      "worldId": 209
    },
    {
      "rowPosition": 0,
      "columnPosition": 2,
      "id": 2,
      "worldId": 209
    },
    {
      "rowPosition": 2,
      "columnPosition": 3,
      "id": 15,
      "worldId": 209
    },
    {
      "rowPosition": 2,
      "columnPosition": 4,
      "id": 16,
      "worldId": 209
    },
    {
      "rowPosition": 2,
      "columnPosition": 2,
      "id": 14,
      "worldId": 209
    }
  ],
  "values": {
    "16": 14.6713249685380002773626983980648219585418701171875,
    "2": 19.02820426374388063095466350205242633819580078125,
    "3": 4.9179249363126320560013482463546097278594970703125,
    "4": 4.05820823735878821736378085915930569171905517578125,
    "7": 8.0362887162579994537736638449132442474365234375,
    "8": 12.061113434933357524414532235823571681976318359375,
    "9": 3.138545119611738432041647683945484459400177001953125,
    "10": 17.375370498715962952474001212976872920989990234375,
    "11": 13.610943153297824892433709464967250823974609375,
    "14": 12.3574663837283740264183506951667368412017822265625,
    "15": 5.2316148858466302584702134481631219387054443359375
  },
  "setupType": "Regional Bidder Setup",
  "population": 0,
  "id": 4,
  "worldId": 209,
  "setup": {
    "valueInterval": {
      "minValue": 3.0,
      "maxValue": 20.0
    },
    "proximitySize": 2,
    "a": 160,
    "b": 4,
    "setupName": "Regional Bidder Setup",
    "numberOfBidders": 5
  },
  "implementation": "org.spectrumauctions.sats.core.model.lsvm.LSVMBidder"
}